axsemantics/__init__.py
axsemantics/base.py
axsemantics/constants.py
axsemantics/errors.py
axsemantics/mixins.py
axsemantics/net.py
axsemantics/resources.py
axsemantics/utils.py
axsemantics-0.1.5.dist-info/DESCRIPTION.rst
axsemantics-0.1.5.dist-info/METADATA
axsemantics-0.1.5.dist-info/RECORD
axsemantics-0.1.5.dist-info/WHEEL
axsemantics-0.1.5.dist-info/metadata.json
axsemantics-0.1.5.dist-info/top_level.txt
