Metadata-Version: 2.0
Name: axsemantics
Version: 0.1.5
Summary: AXSemantics API client
Home-page: https://github.com/axsemantics/axsemantics-python
Author: Tobias Kunze
Author-email: tobias.kunze@ax-semantics.com
License: MIT
Platform: UNKNOWN
Classifier: License :: OSI Approved :: MIT License
Classifier: Programming Language :: Python :: 3
Classifier: Programming Language :: Python :: 3.3
Classifier: Programming Language :: Python :: 3.4
Classifier: Programming Language :: Python :: 3.5
Requires-Dist: click (<7)
Requires-Dist: requests (==2.9.1)
